#summary Java工程师必知必会
#sidebar TableOfContents

=Java工程师必知必会=

==一、Java基础知识==
 # 看一下以下类的源代码
  * java.lang.String
  * java.util.ArrayList & java.util.LinkedList
  * java.util.HashMap & java.util.LinkedHashMap & java.util.TreeMap
  * java.util.HashSet & java.util.LinkedHashSet & java.util.TreeSet
 # Java实现对List排序
 # Java实现对List去重
 # Java实现对List去重，并且需要保留数据原始的出现顺序

==二、Java并发编程==
 # 何为Java内存模型
 # synchronized的作用是什么？
 # volatile的作用是什么？
 # 以下代码是不是线程安全？为什么？如果为count加上volatile修饰是否能够做到线程安全？你觉得该怎么做是线程案例的？
{{{
public class Sample {
  private static int count = 0;

  public static void increment() {
    count++;
  }
}
}}}
 # 学会使用java.uti.concurrent.*

==三、Java底层知识==
 # 了解字节码、class文件格式
 # 写一个程序要求实现javap的功能（手工完成，不借助ASM等工具）
{{{
如Java源代码：
  public static void main(String[] args) {
    int i = 0;
    i += 1;
    i *= 1;
    System.out.println(i);
  }

编译后读取class文件输出以下代码：
public static void main(java.lang.String[]);
  Code:
   Stack=2, Locals=2, Args_size=1
   0:	iconst_0
   1:	istore_1
   2:	iinc	1, 1
   5:	iload_1
   6:	iconst_1
   7:	imul
   8:	istore_1
   9:	getstatic	#2; //Field java/lang/System.out:Ljava/io/PrintStream;
   12:	iload_1
   13:	invokevirtual	#3; //Method java/io/PrintStream.println:(I)V
   16:	return
  LineNumberTable: 
   line 4: 0
   line 5: 2
   line 6: 5
   line 7: 9
   line 8: 16
}}}
 # 使用CGLIB做一个AOP程序
 # 使用ASM实现上述CGLIB实现的功能

==四、网络编程知识==
 # 用Java写一个简单的表态文件的HTTP服务器
  # 实现客户端缓存功能，支持返回304
  # 实现可并发下载一个文件
  # 使用线程池处理客户端请求
  # 使用nio处理客户端请求
  # 支持简单的rewrite规则
 # 用Java实现FTP、SMTP协议
 # 什么是CDN？如果实现？DNS起到什么作用？

==五、网络安全知识==
 # 什么是DES、AES？
 # 什么是RSA、DSA？
 # 什么是MD5，SHA1？
 # 什么是HTTPS、TLS，为什么HTTPS相对安全？
 # 什么是中间人攻击、如果避免中间人攻击？
 # 什么是DOS、DDOS、CC攻击？
 # 什么是CSRF攻击？
 # 什么是CSS攻击？
 # 什么是SQL注入？

==六、JavaScript知识==
 # 什么是prototype？
 # 什么是闭包？
 # 用jQuery写个程序
 # 用node.js写个程序

==七、编译原理知识==
 # 用Java实现以下表达式解析并返回结果（语法和Oracle中的`select sysdate-1 from dual`类似）：
{{{
 sysdate
 sysdate - 1
 sysdate - 1/24
 sysdate - 1/(12*2)
}}}
 # 实现对一个List通过DSL筛选
{{{
  QList<Map<String, Object>> mapList = new QList<Map<String, Object>>;
  mapList.add({"name": "hatter test"});
  mapList.add({"id": -1,"name": "hatter test"});
  mapList.add({"id": 0, "name": "hatter test"});
  mapList.add({"id": 1, "name": "test test"});
  mapList.add({"id": 2, "name": "hatter test"});
  mapList.add({"id": 3, "name": "test hatter"});
  mapList.query("id is not null and id > 0 and name like '%hatter%'");

要求返回列表中匹配的对象，即最后两个对象；
}}}
 # 用Java实现以下程序（语法和变量作用域处理都和JavaScript类似）：
{{{
代码：
var a = 1;
var b = 2;
var c = function() {
  var a = 3;
  println(a);
  println(b);
};
c();
println(a);
println(b);

输出：
3
2
1
2
}}}